jiggybase/__init__.py
jiggybase/chat_stream.py
jiggybase/client.py
jiggybase/collection.py
jiggybase/ijiggy.py
jiggybase/jiggybase_session.py
jiggybase/login.py
jiggybase/org.py
jiggybase/examples/chat_completion.py
jiggybase/examples/chat_completion_stream.py
jiggybase/examples/confluence_sync.py
jiggybase/examples/jiggybase_upload.py
jiggybase/examples/qa_example.py
jiggybase/examples/upload_email_example.py
jiggybase/models/__init__.py
jiggybase/models/auth.py
jiggybase/models/chat.py
jiggybase/models/chatmodel.py
jiggybase/models/chunk.py
jiggybase/models/collection.py
jiggybase/models/embedding.py
jiggybase/models/metadata.py
jiggybase/models/org.py
jiggybase/models/plugin.py
jiggybase/models/plugin_config.py
jiggybase/models/prompt.py
jiggybase/models/providers.py
jiggybase/models/user.py
jiggybase-0.2.1.dist-info/LICENSE
jiggybase-0.2.1.dist-info/METADATA
jiggybase-0.2.1.dist-info/WHEEL
jiggybase-0.2.1.dist-info/entry_points.txt
jiggybase-0.2.1.dist-info/top_level.txt
jiggybase-0.2.1.dist-info/RECORD
