Metadata-Version: 2.1
Name: jiggybase
Version: 0.2.1
Summary: Client for Jiggy AI JiggyBase, including ChatGPT Retriever Plugins
Author-email: Bill Kish <bk@jiggy.ai>
Project-URL: Homepage, https://github.com/jiggy-ai/jiggybase
Project-URL: Bug Tracker, https://github.com/jiggy-ai/issues
Classifier: Programming Language :: Python :: 3
Classifier: License :: OSI Approved :: Apache Software License
Classifier: Operating System :: OS Independent
Requires-Python: >=3.9
License-File: LICENSE
Requires-Dist: loguru
Requires-Dist: pydantic
Requires-Dist: requests
